{
  "_comment": "This file was generated automatically by Supernova.io and should not be changed manually. To modify the format or content of this file, please contact your design system team.",
  "border-width": {
    "border": {
      "stroke": {
        "default": {
          "border-0": {
            "value": "0px",
            "type": "borderWidth"
          },
          "border-2": {
            "value": "2px",
            "type": "borderWidth"
          },
          "border-4": {
            "value": "4px",
            "type": "borderWidth"
          },
          "border-8": {
            "value": "8px",
            "type": "borderWidth"
          },
          "border-16": {
            "value": "16px",
            "type": "borderWidth"
          },
          "border-24": {
            "value": "24px",
            "type": "borderWidth"
          },
          "border-32": {
            "value": "32px",
            "type": "borderWidth"
          },
          "border-40": {
            "value": "40px",
            "type": "borderWidth"
          },
          "border-48": {
            "value": "48px",
            "type": "borderWidth"
          },
          "border-56": {
            "value": "56px",
            "type": "borderWidth"
          },
          "border-64": {
            "value": "64px",
            "type": "borderWidth"
          },
          "border-72": {
            "value": "72px",
            "type": "borderWidth"
          },
          "border-80": {
            "value": "80px",
            "type": "borderWidth"
          }
        },
        "compact": {
          "border-compact-0": {
            "value": "0px",
            "type": "borderWidth"
          },
          "border-compact-2": {
            "value": "2px",
            "type": "borderWidth"
          },
          "border-compact-4": {
            "value": "4px",
            "type": "borderWidth"
          },
          "border-compact-8": {
            "value": "8px",
            "type": "borderWidth"
          },
          "border-compact-12": {
            "value": "12px",
            "type": "borderWidth"
          },
          "border-compact-16": {
            "value": "16px",
            "type": "borderWidth"
          },
          "border-compact-20": {
            "value": "20px",
            "type": "borderWidth"
          },
          "border-compact-24": {
            "value": "24px",
            "type": "borderWidth"
          },
          "border-compact-28": {
            "value": "28px",
            "type": "borderWidth"
          },
          "border-compact-32": {
            "value": "32px",
            "type": "borderWidth"
          },
          "border-compact-36": {
            "value": "36px",
            "type": "borderWidth"
          },
          "border-compact-40": {
            "value": "40px",
            "type": "borderWidth"
          },
          "border-compact-48": {
            "value": "48px",
            "type": "borderWidth"
          }
        }
      },
      "radius": {
        "default": {
          "radius-0": {
            "value": "0px",
            "type": "borderWidth"
          },
          "border-2": {
            "value": "2px",
            "type": "borderWidth"
          },
          "border-4": {
            "value": "4px",
            "type": "borderWidth"
          },
          "border-8": {
            "value": "8px",
            "type": "borderWidth"
          },
          "border-16": {
            "value": "16px",
            "type": "borderWidth"
          },
          "border-24": {
            "value": "24px",
            "type": "borderWidth"
          },
          "border-32": {
            "value": "32px",
            "type": "borderWidth"
          },
          "border-40": {
            "value": "40px",
            "type": "borderWidth"
          },
          "border-48": {
            "value": "48px",
            "type": "borderWidth"
          },
          "border-56": {
            "value": "56px",
            "type": "borderWidth"
          },
          "border-64": {
            "value": "64px",
            "type": "borderWidth"
          },
          "border-72": {
            "value": "72px",
            "type": "borderWidth"
          },
          "border-80": {
            "value": "80px",
            "type": "borderWidth"
          }
        },
        "compact": {
          "border-compact-0": {
            "value": "0px",
            "type": "borderWidth"
          },
          "border-compact-2": {
            "value": "2px",
            "type": "borderWidth"
          },
          "border-compact-4": {
            "value": "4px",
            "type": "borderWidth"
          },
          "border-compact-8": {
            "value": "8px",
            "type": "borderWidth"
          },
          "border-compact-12": {
            "value": "12px",
            "type": "borderWidth"
          },
          "border-compact-16": {
            "value": "16px",
            "type": "borderWidth"
          },
          "border-compact-20": {
            "value": "20px",
            "type": "borderWidth"
          },
          "border-compact-24": {
            "value": "24px",
            "type": "borderWidth"
          },
          "border-compact-28": {
            "value": "28px",
            "type": "borderWidth"
          },
          "border-compact-32": {
            "value": "32px",
            "type": "borderWidth"
          },
          "border-compact-36": {
            "value": "36px",
            "type": "borderWidth"
          },
          "border-compact-40": {
            "value": "40px",
            "type": "borderWidth"
          },
          "border-compact-48": {
            "value": "48px",
            "type": "borderWidth"
          }
        }
      }
    }
  },
  "space": {
    "spacing": {
      "default": {
        "p-0": {
          "value": "0px",
          "type": "space"
        },
        "p-2": {
          "value": "2px",
          "type": "space"
        },
        "p-4": {
          "value": "4px",
          "type": "space"
        },
        "p-8": {
          "value": "8px",
          "type": "space"
        },
        "p-16": {
          "value": "16px",
          "type": "space"
        },
        "p-24": {
          "value": "24px",
          "type": "space"
        },
        "p-32": {
          "value": "32px",
          "type": "space"
        },
        "p-40": {
          "value": "40px",
          "type": "space"
        },
        "p-48": {
          "value": "48px",
          "type": "space"
        },
        "p-56": {
          "value": "56px",
          "type": "space"
        },
        "p-64": {
          "value": "64px",
          "type": "space"
        },
        "p-72": {
          "value": "72px",
          "type": "space"
        },
        "p-80": {
          "value": "80px",
          "type": "space"
        }
      },
      "compact": {
        "p-compact-0": {
          "value": "0px",
          "type": "space"
        },
        "p-compact-2": {
          "value": "2px",
          "type": "space"
        },
        "p-compact-4": {
          "value": "4px",
          "type": "space"
        },
        "p-compact-8": {
          "value": "8px",
          "type": "space"
        },
        "p-compact-12": {
          "value": "12px",
          "type": "space"
        },
        "p-compact-16": {
          "value": "16px",
          "type": "space"
        },
        "p-compact-20": {
          "value": "20px",
          "type": "space"
        },
        "p-compact-24": {
          "value": "24px",
          "type": "space"
        },
        "p-compact-28": {
          "value": "28px",
          "type": "space"
        },
        "p-compact-32": {
          "value": "32px",
          "type": "space"
        },
        "p-compact-36": {
          "value": "36px",
          "type": "space"
        },
        "p-compact-40": {
          "value": "40px",
          "type": "space"
        },
        "p-compact-48": {
          "value": "48px",
          "type": "space"
        }
      }
    }
  },
  "font-size": {
    "font-size": {
      "heading": {
        "font-heading-1": {
          "value": "64px",
          "type": "fontSize"
        },
        "font-heading-2": {
          "value": "56px",
          "type": "fontSize"
        },
        "font-heading-3": {
          "value": "48px",
          "type": "fontSize"
        },
        "font-heading-4": {
          "value": "40px",
          "type": "fontSize"
        },
        "font-heading-5": {
          "value": "32px",
          "type": "fontSize"
        },
        "font-heading-6": {
          "value": "24px",
          "type": "fontSize"
        }
      }
    }
  },
  "dimension": {
    "font-size": {
      "body": {
        "font-body-lg": {
          "value": "18px",
          "type": "dimension"
        },
        "font-body-md": {
          "value": "16px",
          "type": "dimension"
        },
        "font-body-sm": {
          "value": "14px",
          "type": "dimension"
        },
        "font-body-xs": {
          "value": "12px",
          "type": "dimension"
        },
        "font-body-xxs": {
          "value": "10px",
          "type": "dimension"
        }
      }
    },
    "border": {
      "stroke": {
        "default": {
          "border-0_1": {
            "value": "0px",
            "type": "dimension"
          },
          "border-2_1": {
            "value": "0px",
            "type": "dimension"
          },
          "border-4_1": {
            "value": "0px",
            "type": "dimension"
          },
          "border-8_1": {
            "value": "0px",
            "type": "dimension"
          },
          "border-16_1": {
            "value": "0px",
            "type": "dimension"
          },
          "border-24_1": {
            "value": "0px",
            "type": "dimension"
          },
          "border-32_1": {
            "value": "0px",
            "type": "dimension"
          },
          "border-40_1": {
            "value": "0px",
            "type": "dimension"
          },
          "border-48_1": {
            "value": "0px",
            "type": "dimension"
          },
          "border-56_1": {
            "value": "0px",
            "type": "dimension"
          },
          "border-64_1": {
            "value": "0px",
            "type": "dimension"
          },
          "border-72_1": {
            "value": "0px",
            "type": "dimension"
          },
          "border-80_1": {
            "value": "0px",
            "type": "dimension"
          }
        },
        "compact": {
          "border-compact-0_1": {
            "value": "0px",
            "type": "dimension"
          },
          "border-compact-2_1": {
            "value": "0px",
            "type": "dimension"
          },
          "border-compact-4_1": {
            "value": "0px",
            "type": "dimension"
          },
          "border-compact-8_1": {
            "value": "0px",
            "type": "dimension"
          },
          "border-compact-12_1": {
            "value": "0px",
            "type": "dimension"
          },
          "border-compact-16_1": {
            "value": "0px",
            "type": "dimension"
          },
          "border-compact-20_1": {
            "value": "0px",
            "type": "dimension"
          },
          "border-compact-24_1": {
            "value": "0px",
            "type": "dimension"
          },
          "border-compact-28_1": {
            "value": "0px",
            "type": "dimension"
          },
          "border-compact-32_1": {
            "value": "0px",
            "type": "dimension"
          },
          "border-compact-36_1": {
            "value": "0px",
            "type": "dimension"
          },
          "border-compact-40_1": {
            "value": "0px",
            "type": "dimension"
          },
          "border-compact-48_1": {
            "value": "0px",
            "type": "dimension"
          }
        }
      },
      "radius": {
        "default": {
          "radius-0_1": {
            "value": "0px",
            "type": "dimension"
          },
          "border-2_1": {
            "value": "0px",
            "type": "dimension"
          },
          "border-4_1": {
            "value": "0px",
            "type": "dimension"
          },
          "border-8_1": {
            "value": "0px",
            "type": "dimension"
          },
          "border-16_1": {
            "value": "0px",
            "type": "dimension"
          },
          "border-24_1": {
            "value": "0px",
            "type": "dimension"
          },
          "border-32_1": {
            "value": "0px",
            "type": "dimension"
          },
          "border-40_1": {
            "value": "0px",
            "type": "dimension"
          },
          "border-48_1": {
            "value": "0px",
            "type": "dimension"
          },
          "border-56_1": {
            "value": "0px",
            "type": "dimension"
          },
          "border-64_1": {
            "value": "0px",
            "type": "dimension"
          },
          "border-72_1": {
            "value": "0px",
            "type": "dimension"
          },
          "border-80_1": {
            "value": "0px",
            "type": "dimension"
          }
        },
        "compact": {
          "border-compact-0_1": {
            "value": "0px",
            "type": "dimension"
          },
          "border-compact-2_1": {
            "value": "0px",
            "type": "dimension"
          },
          "border-compact-4_1": {
            "value": "0px",
            "type": "dimension"
          },
          "border-compact-8_1": {
            "value": "0px",
            "type": "dimension"
          },
          "border-compact-12_1": {
            "value": "0px",
            "type": "dimension"
          },
          "border-compact-16_1": {
            "value": "0px",
            "type": "dimension"
          },
          "border-compact-20_1": {
            "value": "0px",
            "type": "dimension"
          },
          "border-compact-24_1": {
            "value": "0px",
            "type": "dimension"
          },
          "border-compact-28_1": {
            "value": "0px",
            "type": "dimension"
          },
          "border-compact-32_1": {
            "value": "0px",
            "type": "dimension"
          },
          "border-compact-36_1": {
            "value": "0px",
            "type": "dimension"
          },
          "border-compact-40_1": {
            "value": "0px",
            "type": "dimension"
          },
          "border-compact-48_1": {
            "value": "0px",
            "type": "dimension"
          }
        }
      }
    },
    "spacing": {
      "default": {
        "p-0_1": {
          "value": "0px",
          "type": "dimension"
        },
        "p-80_1": {
          "value": "0px",
          "type": "dimension"
        },
        "p-32_1": {
          "value": "0px",
          "type": "dimension"
        },
        "p-56_1": {
          "value": "0px",
          "type": "dimension"
        },
        "p-48_1": {
          "value": "0px",
          "type": "dimension"
        },
        "p-40_1": {
          "value": "0px",
          "type": "dimension"
        },
        "p-24_1": {
          "value": "0px",
          "type": "dimension"
        },
        "p-8_1": {
          "value": "0px",
          "type": "dimension"
        },
        "p-16_1": {
          "value": "0px",
          "type": "dimension"
        },
        "p-4_1": {
          "value": "0px",
          "type": "dimension"
        },
        "p-72_1": {
          "value": "0px",
          "type": "dimension"
        },
        "p-64_1": {
          "value": "0px",
          "type": "dimension"
        },
        "p-2_1": {
          "value": "0px",
          "type": "dimension"
        }
      },
      "compact": {
        "p-compact-0_1": {
          "value": "0px",
          "type": "dimension"
        },
        "p-compact-2_1": {
          "value": "0px",
          "type": "dimension"
        },
        "p-compact-36_1": {
          "value": "0px",
          "type": "dimension"
        },
        "p-compact-40_1": {
          "value": "0px",
          "type": "dimension"
        },
        "p-compact-48_1": {
          "value": "0px",
          "type": "dimension"
        },
        "p-compact-24_1": {
          "value": "0px",
          "type": "dimension"
        },
        "p-compact-28_1": {
          "value": "0px",
          "type": "dimension"
        },
        "p-compact-32_1": {
          "value": "0px",
          "type": "dimension"
        },
        "p-compact-4_1": {
          "value": "0px",
          "type": "dimension"
        },
        "p-compact-8_1": {
          "value": "0px",
          "type": "dimension"
        },
        "p-compact-12_1": {
          "value": "0px",
          "type": "dimension"
        },
        "p-compact-16_1": {
          "value": "0px",
          "type": "dimension"
        },
        "p-compact-20_1": {
          "value": "0px",
          "type": "dimension"
        }
      }
    },
    "fontsize": {
      "heading": {
        "font-heading-1": {
          "value": "0px",
          "type": "dimension"
        },
        "font-heading-2": {
          "value": "0px",
          "type": "dimension"
        },
        "font-heading-3": {
          "value": "0px",
          "type": "dimension"
        },
        "font-heading-4": {
          "value": "0px",
          "type": "dimension"
        },
        "font-heading-5": {
          "value": "0px",
          "type": "dimension"
        },
        "font-heading-6": {
          "value": "0px",
          "type": "dimension"
        }
      },
      "body": {
        "font-body-lg": {
          "value": "0px",
          "type": "dimension"
        },
        "font-body-md": {
          "value": "0px",
          "type": "dimension"
        },
        "font-body-sm": {
          "value": "0px",
          "type": "dimension"
        },
        "font-body-xs": {
          "value": "0px",
          "type": "dimension"
        },
        "font-body-xxs": {
          "value": "0px",
          "type": "dimension"
        }
      }
    },
    "borders": {
      "stroke": {
        "default": {
          "border-0": {
            "value": "0px",
            "type": "dimension"
          },
          "border-2": {
            "value": "0px",
            "type": "dimension"
          },
          "border-4": {
            "value": "0px",
            "type": "dimension"
          },
          "border-8": {
            "value": "0px",
            "type": "dimension"
          },
          "border-16": {
            "value": "0px",
            "type": "dimension"
          },
          "border-24": {
            "value": "0px",
            "type": "dimension"
          },
          "border-32": {
            "value": "0px",
            "type": "dimension"
          },
          "border-40": {
            "value": "0px",
            "type": "dimension"
          },
          "border-48": {
            "value": "0px",
            "type": "dimension"
          },
          "border-56": {
            "value": "0px",
            "type": "dimension"
          },
          "border-64": {
            "value": "0px",
            "type": "dimension"
          },
          "border-72": {
            "value": "0px",
            "type": "dimension"
          },
          "border-80": {
            "value": "0px",
            "type": "dimension"
          }
        },
        "compact": {
          "border-compact-0": {
            "value": "0px",
            "type": "dimension"
          },
          "border-compact-2": {
            "value": "0px",
            "type": "dimension"
          },
          "border-compact-4": {
            "value": "0px",
            "type": "dimension"
          },
          "border-compact-8": {
            "value": "0px",
            "type": "dimension"
          },
          "border-compact-12": {
            "value": "0px",
            "type": "dimension"
          },
          "border-compact-16": {
            "value": "0px",
            "type": "dimension"
          },
          "border-compact-20": {
            "value": "0px",
            "type": "dimension"
          },
          "border-compact-24": {
            "value": "0px",
            "type": "dimension"
          },
          "border-compact-28": {
            "value": "0px",
            "type": "dimension"
          },
          "border-compact-32": {
            "value": "0px",
            "type": "dimension"
          },
          "border-compact-36": {
            "value": "0px",
            "type": "dimension"
          },
          "border-compact-40": {
            "value": "0px",
            "type": "dimension"
          },
          "border-compact-48": {
            "value": "0px",
            "type": "dimension"
          }
        }
      },
      "radius": {
        "default": {
          "radius-0": {
            "value": "0px",
            "type": "dimension"
          },
          "border-2": {
            "value": "0px",
            "type": "dimension"
          },
          "border-4": {
            "value": "0px",
            "type": "dimension"
          },
          "border-8": {
            "value": "0px",
            "type": "dimension"
          },
          "border-16": {
            "value": "0px",
            "type": "dimension"
          },
          "border-24": {
            "value": "0px",
            "type": "dimension"
          },
          "border-32": {
            "value": "0px",
            "type": "dimension"
          },
          "border-40": {
            "value": "0px",
            "type": "dimension"
          },
          "border-48": {
            "value": "0px",
            "type": "dimension"
          },
          "border-56": {
            "value": "0px",
            "type": "dimension"
          },
          "border-64": {
            "value": "0px",
            "type": "dimension"
          },
          "border-72": {
            "value": "0px",
            "type": "dimension"
          },
          "border-80": {
            "value": "0px",
            "type": "dimension"
          }
        },
        "compact": {
          "border-compact-0": {
            "value": "0px",
            "type": "dimension"
          },
          "border-compact-2": {
            "value": "0px",
            "type": "dimension"
          },
          "border-compact-4": {
            "value": "0px",
            "type": "dimension"
          },
          "border-compact-8": {
            "value": "0px",
            "type": "dimension"
          },
          "border-compact-12": {
            "value": "0px",
            "type": "dimension"
          },
          "border-compact-16": {
            "value": "0px",
            "type": "dimension"
          },
          "border-compact-20": {
            "value": "0px",
            "type": "dimension"
          },
          "border-compact-24": {
            "value": "0px",
            "type": "dimension"
          },
          "border-compact-28": {
            "value": "0px",
            "type": "dimension"
          },
          "border-compact-32": {
            "value": "0px",
            "type": "dimension"
          },
          "border-compact-36": {
            "value": "0px",
            "type": "dimension"
          },
          "border-compact-40": {
            "value": "0px",
            "type": "dimension"
          },
          "border-compact-48": {
            "value": "0px",
            "type": "dimension"
          }
        }
      }
    }
  },
  "color": {
    "charcoal": {
      "400": {
        "value": "#a3a3a3",
        "type": "color"
      }
    },
    "b-w": {
      "white": {
        "value": "#ffffff",
        "type": "color"
      }
    },
    "grey": {
      "700": {
        "value": "#3c3c3c",
        "type": "color"
      },
      "900": {
        "value": "#171717",
        "type": "color"
      }
    },
    "cool-gray": {
      "700": {
        "value": "#4a5568",
        "type": "color"
      },
      "white": {
        "value": "#ffffff",
        "type": "color"
      }
    },
    "illustrations": {
      "grey": {
        "700-base": {
          "value": "#3a3637",
          "type": "color"
        }
      }
    },
    "core": {
      "color": {
        "red": {
          "50": {
            "value": "#f5dbd9",
            "type": "color"
          },
          "100": {
            "value": "#ebb9b3",
            "type": "color"
          },
          "200": {
            "value": "#e2958d",
            "type": "color"
          },
          "300": {
            "value": "#da7368",
            "type": "color"
          },
          "400": {
            "value": "#d35445",
            "type": "color"
          },
          "500": {
            "value": "#d52b1e",
            "type": "color"
          },
          "600": {
            "value": "#d52b1e",
            "type": "color"
          },
          "700": {
            "value": "#621d15",
            "type": "color"
          },
          "800": {
            "value": "#41120d",
            "type": "color"
          },
          "900": {
            "value": "#210906",
            "type": "color"
          },
          "50_1": {
            "value": "#ffffff",
            "type": "color"
          },
          "100_1": {
            "value": "#ffffff",
            "type": "color"
          },
          "200_1": {
            "value": "#ffffff",
            "type": "color"
          },
          "300_1": {
            "value": "#ffffff",
            "type": "color"
          },
          "400_1": {
            "value": "#ffffff",
            "type": "color"
          },
          "500_1": {
            "value": "#ffffff",
            "type": "color"
          },
          "600_1": {
            "value": "#ffffff",
            "type": "color"
          },
          "700_1": {
            "value": "#ffffff",
            "type": "color"
          },
          "800_1": {
            "value": "#ffffff",
            "type": "color"
          },
          "900_1": {
            "value": "#ffffff",
            "type": "color"
          }
        },
        "cool-grey-4": {
          "50": {
            "value": "#f4f4f4",
            "type": "color"
          },
          "100": {
            "value": "#e9e9e9",
            "type": "color"
          },
          "200": {
            "value": "#dedede",
            "type": "color"
          },
          "300": {
            "value": "#d2d3d2",
            "type": "color"
          },
          "400": {
            "value": "#c7c8c7",
            "type": "color"
          },
          "500": {
            "value": "#bcbdbc",
            "type": "color"
          },
          "600": {
            "value": "#8d8e8d",
            "type": "color"
          },
          "700": {
            "value": "#767775",
            "type": "color"
          },
          "800": {
            "value": "#5e5f5e",
            "type": "color"
          },
          "900": {
            "value": "#464746",
            "type": "color"
          },
          "50_1": {
            "value": "#ffffff",
            "type": "color"
          },
          "100_1": {
            "value": "#ffffff",
            "type": "color"
          },
          "200_1": {
            "value": "#ffffff",
            "type": "color"
          },
          "300_1": {
            "value": "#ffffff",
            "type": "color"
          },
          "400_1": {
            "value": "#ffffff",
            "type": "color"
          },
          "500_1": {
            "value": "#ffffff",
            "type": "color"
          },
          "600_1": {
            "value": "#ffffff",
            "type": "color"
          },
          "700_1": {
            "value": "#ffffff",
            "type": "color"
          },
          "800_1": {
            "value": "#ffffff",
            "type": "color"
          },
          "900_1": {
            "value": "#ffffff",
            "type": "color"
          }
        },
        "cool-grey-10": {
          "50": {
            "value": "#e4e5e6",
            "type": "color"
          },
          "100": {
            "value": "#cacbcc",
            "type": "color"
          },
          "200": {
            "value": "#b0b1b3",
            "type": "color"
          },
          "300": {
            "value": "#969799",
            "type": "color"
          },
          "400": {
            "value": "#7b7d80",
            "type": "color"
          },
          "500": {
            "value": "#616365",
            "type": "color"
          },
          "600": {
            "value": "#494a4c",
            "type": "color"
          },
          "700": {
            "value": "#3d3e3f",
            "type": "color"
          },
          "800": {
            "value": "#313132",
            "type": "color"
          },
          "900": {
            "value": "#242526",
            "type": "color"
          },
          "50_1": {
            "value": "#ffffff",
            "type": "color"
          },
          "100_1": {
            "value": "#ffffff",
            "type": "color"
          },
          "200_1": {
            "value": "#ffffff",
            "type": "color"
          },
          "300_1": {
            "value": "#ffffff",
            "type": "color"
          },
          "400_1": {
            "value": "#ffffff",
            "type": "color"
          },
          "500_1": {
            "value": "#ffffff",
            "type": "color"
          },
          "600_1": {
            "value": "#ffffff",
            "type": "color"
          },
          "700_1": {
            "value": "#ffffff",
            "type": "color"
          },
          "800_1": {
            "value": "#ffffff",
            "type": "color"
          },
          "900_1": {
            "value": "#ffffff",
            "type": "color"
          }
        },
        "neutral": {
          "white": {
            "value": "#ffffff",
            "type": "color"
          },
          "black": {
            "value": "#1e1e1e",
            "type": "color"
          },
          "white_1": {
            "value": "#ffffff",
            "type": "color"
          },
          "black_1": {
            "value": "#ffffff",
            "type": "color"
          }
        },
        "status": {
          "green": {
            "value": "#006b4d",
            "type": "color"
          },
          "orange": {
            "value": "#e15d00",
            "type": "color"
          },
          "red": {
            "value": "#da1307",
            "type": "color"
          },
          "blue": {
            "value": "#18488f",
            "type": "color"
          },
          "green_1": {
            "value": "#ffffff",
            "type": "color"
          },
          "red_1": {
            "value": "#ffffff",
            "type": "color"
          },
          "orange_1": {
            "value": "#ffffff",
            "type": "color"
          },
          "blue_1": {
            "value": "#ffffff",
            "type": "color"
          },
          "yellow": {
            "value": "#dccd2f",
            "type": "color"
          }
        }
      }
    },
    "semantics": {
      "light": {
        "surface": {
          "button": {
            "primary": {
              "default": {
                "value": "#ffffff",
                "type": "color"
              },
              "hover": {
                "value": "#ffffff",
                "type": "color"
              },
              "active": {
                "value": "#ffffff",
                "type": "color"
              },
              "disabled": {
                "value": "#ffffff",
                "type": "color"
              }
            },
            "secondary": {
              "default": {
                "value": "#ffffff",
                "type": "color"
              },
              "hover": {
                "value": "#ffffff",
                "type": "color"
              },
              "active": {
                "value": "#ffffff",
                "type": "color"
              },
              "disabled": {
                "value": "#ffffff",
                "type": "color"
              }
            }
          }
        },
        "text": {
          "button": {
            "primary": {
              "default": {
                "value": "#ffffff",
                "type": "color"
              },
              "disabled": {
                "value": "#ffffff",
                "type": "color"
              },
              "hover-active": {
                "value": "#ffffff",
                "type": "color"
              }
            },
            "secondary": {
              "default": {
                "value": "#ffffff",
                "type": "color"
              },
              "disabled": {
                "value": "#ffffff",
                "type": "color"
              },
              "hover": {
                "value": "#ffffff",
                "type": "color"
              },
              "clicked": {
                "value": "#ffffff",
                "type": "color"
              }
            },
            "link": {
              "default": {
                "value": "#ffffff",
                "type": "color"
              },
              "hover": {
                "value": "#ffffff",
                "type": "color"
              },
              "clicked": {
                "value": "#ffffff",
                "type": "color"
              },
              "disabled": {
                "value": "#ffffff",
                "type": "color"
              }
            }
          },
          "heading": {
            "primary": {
              "value": "#ffffff",
              "type": "color"
            },
            "secondary": {
              "value": "#ffffff",
              "type": "color"
            }
          },
          "body": {
            "primary": {
              "value": "#ffffff",
              "type": "color"
            },
            "secondary": {
              "value": "#ffffff",
              "type": "color"
            }
          },
          "legal": {
            "primary": {
              "value": "#ffffff",
              "type": "color"
            }
          },
          "status": {
            "success": {
              "value": "#ffffff",
              "type": "color"
            },
            "warning": {
              "value": "#ffffff",
              "type": "color"
            },
            "error": {
              "value": "#ffffff",
              "type": "color"
            },
            "info": {
              "value": "#ffffff",
              "type": "color"
            }
          }
        },
        "border": {
          "form-assets": {
            "inputs-text-areas": {
              "value": "#ffffff",
              "type": "color"
            },
            "error": {
              "value": "#ffffff",
              "type": "color"
            }
          },
          "button": {
            "outlined": {
              "default": {
                "value": "#ffffff",
                "type": "color"
              },
              "hover": {
                "value": "#ffffff",
                "type": "color"
              },
              "active": {
                "value": "#ffffff",
                "type": "color"
              },
              "disabled": {
                "value": "#ffffff",
                "type": "color"
              }
            }
          },
          "status": {
            "info": {
              "value": "#ffffff",
              "type": "color"
            },
            "success": {
              "value": "#ffffff",
              "type": "color"
            },
            "warning": {
              "value": "#ffffff",
              "type": "color"
            },
            "error": {
              "value": "#ffffff",
              "type": "color"
            },
            "offer": {
              "value": "#ffffff",
              "type": "color"
            }
          }
        },
        "content": {
          "button": {
            "icon": {
              "primary": {
                "default-hover-active": {
                  "value": "#ffffff",
                  "type": "color"
                },
                "disabled": {
                  "value": "#ffffff",
                  "type": "color"
                }
              },
              "secondary": {
                "default-hover-active": {
                  "value": "#ffffff",
                  "type": "color"
                },
                "disabled": {
                  "value": "#ffffff",
                  "type": "color"
                }
              }
            }
          }
        }
      },
      "dark": {
        "surface": {
          "button": {
            "primary": {
              "default": {
                "value": "#ffffff",
                "type": "color"
              },
              "hover": {
                "value": "#ffffff",
                "type": "color"
              },
              "active": {
                "value": "#ffffff",
                "type": "color"
              },
              "disabled": {
                "value": "#ffffff",
                "type": "color"
              }
            },
            "secondary": {
              "default": {
                "value": "#ffffff",
                "type": "color"
              },
              "hover": {
                "value": "#ffffff",
                "type": "color"
              },
              "active": {
                "value": "#ffffff",
                "type": "color"
              },
              "disabled": {
                "value": "#ffffff",
                "type": "color"
              }
            }
          }
        },
        "text": {
          "button": {
            "primary": {
              "default": {
                "value": "#ffffff",
                "type": "color"
              },
              "disabled": {
                "value": "#ffffff",
                "type": "color"
              },
              "hover-active": {
                "value": "#ffffff",
                "type": "color"
              }
            },
            "secondary": {
              "default": {
                "value": "#ffffff",
                "type": "color"
              },
              "disabled": {
                "value": "#ffffff",
                "type": "color"
              },
              "hover": {
                "value": "#ffffff",
                "type": "color"
              },
              "clicked": {
                "value": "#ffffff",
                "type": "color"
              }
            },
            "link": {
              "default": {
                "value": "#ffffff",
                "type": "color"
              },
              "hover": {
                "value": "#ffffff",
                "type": "color"
              },
              "clicked": {
                "value": "#ffffff",
                "type": "color"
              },
              "disabled": {
                "value": "#ffffff",
                "type": "color"
              }
            }
          },
          "heading": {
            "primary": {
              "value": "#ffffff",
              "type": "color"
            },
            "secondary": {
              "value": "#ffffff",
              "type": "color"
            }
          },
          "body": {
            "primary": {
              "value": "#ffffff",
              "type": "color"
            },
            "secondary": {
              "value": "#ffffff",
              "type": "color"
            }
          },
          "legal": {
            "primary": {
              "value": "#ffffff",
              "type": "color"
            }
          },
          "status": {
            "success": {
              "value": "#ffffff",
              "type": "color"
            },
            "warning": {
              "value": "#ffffff",
              "type": "color"
            },
            "error": {
              "value": "#ffffff",
              "type": "color"
            },
            "info": {
              "value": "#ffffff",
              "type": "color"
            }
          }
        },
        "border": {
          "form-assets": {
            "inputs-text-areas": {
              "value": "#ffffff",
              "type": "color"
            },
            "error": {
              "value": "#ffffff",
              "type": "color"
            }
          },
          "button": {
            "outlined": {
              "default": {
                "value": "#ffffff",
                "type": "color"
              },
              "hover": {
                "value": "#ffffff",
                "type": "color"
              },
              "active": {
                "value": "#ffffff",
                "type": "color"
              },
              "disabled": {
                "value": "#ffffff",
                "type": "color"
              }
            }
          },
          "status": {
            "info": {
              "value": "#ffffff",
              "type": "color"
            },
            "success": {
              "value": "#ffffff",
              "type": "color"
            },
            "warning": {
              "value": "#ffffff",
              "type": "color"
            },
            "error": {
              "value": "#ffffff",
              "type": "color"
            },
            "offer": {
              "value": "#ffffff",
              "type": "color"
            }
          }
        },
        "content": {
          "button": {
            "icon": {
              "primary": {
                "default-hover-active": {
                  "value": "#ffffff",
                  "type": "color"
                },
                "disabled": {
                  "value": "#ffffff",
                  "type": "color"
                }
              },
              "secondary": {
                "default-hover-active": {
                  "value": "#ffffff",
                  "type": "color"
                },
                "disabled": {
                  "value": "#ffffff",
                  "type": "color"
                }
              }
            }
          }
        }
      }
    },
    "surface": {
      "button": {
        "primary": {
          "default": {
            "value": "{color.core.color.red.500}",
            "type": "color"
          },
          "hover": {
            "value": "{color.core.color.red.400}",
            "type": "color"
          },
          "active": {
            "value": "{color.core.color.red.700}",
            "type": "color"
          },
          "disabled": {
            "value": "{color.core.color.cool-grey-10.50}",
            "type": "color"
          }
        },
        "secondary": {
          "default": {
            "value": "{color.core.color.red.500}",
            "type": "color"
          },
          "hover": {
            "value": "{color.core.color.red.400}",
            "type": "color"
          },
          "active": {
            "value": "{color.core.color.red.700}",
            "type": "color"
          },
          "disabled": {
            "value": "{color.core.color.cool-grey-4.800}",
            "type": "color"
          }
        }
      }
    },
    "border": {
      "button": {
        "outlined": {
          "default": {
            "value": "{color.core.color.red.500}",
            "type": "color"
          },
          "hover": {
            "value": "{color.core.color.red.400}",
            "type": "color"
          },
          "active": {
            "value": "{color.core.color.red.700}",
            "type": "color"
          },
          "disabled": {
            "value": "{color.core.color.cool-grey-10.300}",
            "type": "color"
          }
        }
      },
      "form-assets": {
        "inputs-text-areas": {
          "value": "{color.core.color.cool-grey-10.300}",
          "type": "color"
        },
        "error": {
          "value": "{color.core.color.status.red}",
          "type": "color"
        }
      },
      "status": {
        "success": {
          "value": "{color.core.color.status.green}",
          "type": "color"
        },
        "warning": {
          "value": "{color.core.color.status.orange}",
          "type": "color"
        },
        "info": {
          "value": "{color.core.color.status.blue}",
          "type": "color"
        },
        "error": {
          "value": "{color.core.color.status.red}",
          "type": "color"
        },
        "offer": {
          "value": "{color.core.color.red.500}",
          "type": "color"
        }
      }
    },
    "text": {
      "legal": {
        "primary": {
          "value": "{color.core.color.neutral.black}",
          "type": "color"
        }
      },
      "heading": {
        "primary": {
          "value": "{color.core.color.neutral.black}",
          "type": "color"
        },
        "secondary": {
          "value": "{color.core.color.neutral.black}",
          "type": "color"
        }
      },
      "body": {
        "primary": {
          "value": "{color.core.color.neutral.black}",
          "type": "color"
        },
        "secondary": {
          "value": "{color.core.color.neutral.black}",
          "type": "color"
        }
      },
      "status": {
        "success": {
          "value": "{color.core.color.status.green}",
          "type": "color"
        },
        "warning": {
          "value": "{color.core.color.status.orange}",
          "type": "color"
        },
        "error": {
          "value": "{color.core.color.status.red}",
          "type": "color"
        },
        "info": {
          "value": "{color.core.color.status.blue}",
          "type": "color"
        }
      },
      "button": {
        "primary": {
          "default": {
            "value": "{color.core.color.neutral.white}",
            "type": "color"
          },
          "hover-active": {
            "value": "{color.core.color.neutral.white}",
            "type": "color"
          },
          "disabled": {
            "value": "{color.core.color.cool-grey-10.300}",
            "type": "color"
          }
        },
        "secondary": {
          "default": {
            "value": "{color.core.color.neutral.black}",
            "type": "color"
          },
          "hover": {
            "value": "{color.core.color.red.500}",
            "type": "color"
          },
          "clicked": {
            "value": "{color.core.color.red.600}",
            "type": "color"
          },
          "disabled": {
            "value": "{color.core.color.cool-grey-10.300}",
            "type": "color"
          }
        },
        "link": {
          "default": {
            "value": "{color.core.color.red.500}",
            "type": "color"
          },
          "hover": {
            "value": "{color.core.color.red.400}",
            "type": "color"
          },
          "clicked": {
            "value": "{color.core.color.red.700}",
            "type": "color"
          },
          "disabled": {
            "value": "{color.core.color.cool-grey-10.300}",
            "type": "color"
          }
        }
      }
    },
    "content": {
      "button": {
        "icon": {
          "primary": {
            "default-hover-active": {
              "value": "{color.core.color.neutral.white}",
              "type": "color"
            },
            "disabled": {
              "value": "{color.core.color.cool-grey-10.300}",
              "type": "color"
            }
          },
          "secondary": {
            "default-hover-active": {
              "value": "{color.core.color.red.500}",
              "type": "color"
            },
            "disabled": {
              "value": "{color.core.color.cool-grey-10.300}",
              "type": "color"
            }
          }
        }
      }
    }
  },
  "typography": {
    "play-text-xl": {
      "400": {
        "value": "400 {fontSize.font-size.heading.font-heading-6}/34px Play",
        "type": "typography",
        "description": "This is heading 5 font size"
      },
      "700": {
        "value": "700 24px/34px Play",
        "type": "typography",
        "description": "This is heading 6 font size"
      }
    },
    "ubuntu-text-lg": {
      "700": {
        "value": "700 {dimension.font-size.body.font-body-lg}/28px Ubuntu Sans",
        "type": "typography",
        "description": "This is font size for intros"
      }
    },
    "ubuntu-textlink-lg": {
      "500": {
        "value": "500 18px/28px Ubuntu Sans",
        "type": "typography"
      }
    },
    "ubuntu-text-base": {
      "700": {
        "value": "700 {dimension.font-size.body.font-body-md}/26px Ubuntu Sans",
        "type": "typography"
      }
    },
    "ubuntu-textlink-base": {
      "500": {
        "value": "500 16px/26px Ubuntu Sans",
        "type": "typography"
      }
    },
    "ubuntu-text-sm": {
      "700": {
        "value": "700 14px/24px Ubuntu Sans",
        "type": "typography"
      }
    },
    "ubuntu-textlink-sm": {
      "500": {
        "value": "500 14px/24px Ubuntu Sans",
        "type": "typography"
      }
    },
    "play-text-3xl": {
      "400": {
        "value": "400 {fontSize.font-size.heading.font-heading-4}/50px Play",
        "type": "typography",
        "description": "This is heading 3 font size"
      }
    },
    "heading": {
      "h2": {
        "archive-title": {
          "desktop": {
            "value": "400 32px/28px Whitney SSm",
            "type": "typography"
          }
        }
      },
      "h1": {
        "semibold": {
          "mobile": {
            "value": "700 36px/34.2px Whitney SSm",
            "type": "typography"
          }
        }
      }
    },
    "label": {
      "large": {
        "medium": {
          "value": "350 18px/28px Whitney SSm",
          "type": "typography"
        },
        "underline": {
          "medium": {
            "value": "350 18px/28px Whitney SSm",
            "type": "typography"
          }
        }
      },
      "medium": {
        "medium": {
          "value": "350 16px/24px Whitney SSm",
          "type": "typography"
        },
        "underline": {
          "medium": {
            "value": "350 16px/24px Whitney SSm",
            "type": "typography"
          }
        }
      },
      "small": {
        "medium": {
          "value": "350 14px/20px Whitney SSm",
          "type": "typography"
        },
        "underline": {
          "medium": {
            "value": "350 14px/20px Whitney SSm",
            "type": "typography"
          }
        }
      }
    }
  }
}